GUI/__init__.py
GUI/sphere_overburden_gui.py
resources/__init__.py
resources/resources.py
utils/__init__.py
utils/sphere_response.py
sphereob-0.1.2.dist-info/LICENSE
sphereob-0.1.2.dist-info/METADATA
sphereob-0.1.2.dist-info/WHEEL
sphereob-0.1.2.dist-info/entry_points.txt
sphereob-0.1.2.dist-info/top_level.txt
sphereob-0.1.2.dist-info/RECORD
