Metadata-Version: 2.1
Name: sphereob
Version: 0.1.2
Summary: A description of your project
Home-page: https://github.com/yourusername/sphereob
Author: Your Name
Author-email: your.email@example.com
Classifier: Programming Language :: Python :: 3
Classifier: License :: OSI Approved :: MIT License
Classifier: Operating System :: OS Independent
Requires-Python: >=3.6
License-File: LICENSE
Requires-Dist: PyQt5
Requires-Dist: numpy
Requires-Dist: matplotlib
Requires-Dist: pandas
Requires-Dist: qdarkstyle
Requires-Dist: scipy
